AUTHORS.rst
CONTRIBUTING.rst
HISTORY.rst
LICENSE
MANIFEST.in
README.rst
setup.cfg
setup.py
docs/Makefile
docs/authors.rst
docs/conf.py
docs/contributing.rst
docs/history.rst
docs/index.rst
docs/installation.rst
docs/make.bat
docs/readme.rst
docs/usage.rst
tests/__init__.py
tests/test_tinytv.py
tinytv/__init__.py
tinytv/tinytv.py
tinytv.egg-info/PKG-INFO
tinytv.egg-info/SOURCES.txt
tinytv.egg-info/dependency_links.txt
tinytv.egg-info/entry_points.txt
tinytv.egg-info/not-zip-safe
tinytv.egg-info/requires.txt
tinytv.egg-info/top_level.txt