Metadata-Version: 1.1
Name: tinytv
Version: 0.1.5
Summary: Ncurses interface to streaming torrents with imdb, showrss and magnet lists support
Home-page: https://github.com/XayOn/tinytv
Author: David Francos Cuartero
Author-email: me@davidfrancos.net
License: BSD
Keywords: tinytv
Platform: UNKNOWN
Classifier: Development Status :: 2 - Pre-Alpha
Classifier: Intended Audience :: Developers
Classifier: License :: OSI Approved :: BSD License
Classifier: Natural Language :: English
Classifier: Programming Language :: Python :: 2
Classifier: Programming Language :: Python :: 2.6
Classifier: Programming Language :: Python :: 2.7
Classifier: Programming Language :: Python :: 3
Classifier: Programming Language :: Python :: 3.3
Classifier: Programming Language :: Python :: 3.4
